pairplex/__init__.py
pairplex/count_features.py
pairplex/make_fastq.py
pairplex/pairplex.py
pairplex/utils.py
pairplex/version.py
pairplex/barcodes/3M-5pgex-jan-2023.txt
pairplex/barcodes/3M-5pgex-jan-2023.txt.gz
pairplex/barcodes/737K-august-2016.txt
pairplex/data/RunManifest.csv
pairplex/data/SampleSheet.csv
pairplex/data/Samples.yaml
pairplex/data/feature_barcodes.csv
pairplex/data/pairplex_logo.png
pairplex/data/pairplex_logo.psd
pairplex/data/pairplex_logo_borders.png
pairplex/data/pairplex_logo_borders_eyelashes.png
pairplex/data/pairplex_logo_old.png
pairplex/scripts/__init__.py
pairplex/scripts/pairplex.py
pairplex/tests/__init__.py
pairplex/tests/test_utils.py
pairplex-0.1.1.dist-info/licenses/LICENSE
pairplex-0.1.1.dist-info/METADATA
pairplex-0.1.1.dist-info/WHEEL
pairplex-0.1.1.dist-info/entry_points.txt
pairplex-0.1.1.dist-info/top_level.txt
pairplex-0.1.1.dist-info/RECORD
