Metadata-Version: 2.4
Name: pairplex
Version: 0.1.1
Summary: Demultiplex single-cell antibody repertoires with precision and paired insight.
Home-page: https://github.com/brineylab/pairplex
Author: Benjamin Nemoz
Author-email: bnemoz@scripps.edu
Classifier: Development Status :: 4 - Beta
Classifier: Intended Audience :: Science/Research
Classifier: License :: OSI Approved :: MIT License
Classifier: Operating System :: OS Independent
Classifier: Programming Language :: Python :: 3
Classifier: Programming Language :: Python :: 3.10
Classifier: Programming Language :: Python :: 3.11
Classifier: Programming Language :: Python :: 3.12
Classifier: Programming Language :: Python :: 3.13
Classifier: Topic :: Scientific/Engineering :: Bio-Informatics
Requires-Python: >=3.11
License-File: LICENSE
Requires-Dist: abstar>=0.7.3
Requires-Dist: abutils>=0.5.3
Requires-Dist: click
Requires-Dist: natsort
Requires-Dist: polars
Requires-Dist: tqdm
Dynamic: author
Dynamic: author-email
Dynamic: classifier
Dynamic: description
Dynamic: description-content-type
Dynamic: home-page
Dynamic: license-file
Dynamic: requires-dist
Dynamic: requires-python
Dynamic: summary
